django_memoize-2.2.0.dist-info/metadata.json
django_memoize-2.2.0.dist-info/RECORD
django_memoize-2.2.0.dist-info/DESCRIPTION.rst
django_memoize-2.2.0.dist-info/top_level.txt
django_memoize-2.2.0.dist-info/WHEEL
django_memoize-2.2.0.dist-info/METADATA
memoize/__init__.py
